{"hash":"d6aa8e960daca7bb64644ab13c035a6c66a1d2a7","data":{"clube":{"id":"294","nome_fantasia":"Coritiba","clube_abrev":"COR","escudo_60":"https://s.sde.globo.com/media/organizations/2017/03/29/coritiba65.png","posicao":19,"atletas":[{"id":101254,"apelido":"Alef Manga","posicao":"Atacante","posicao_abrev":"ata","foto":"https://s.sde.globo.com/media/person_role/2023/02/28/photo_220x220_o07AeW3.png","pontos_num":0,"preco_num":10.37,"variacao_num":0,"media_num":6.05,"jogos_num":4},{"id":93787,"apelido":"Andrey","posicao":"Meia","posicao_abrev":"mei","foto":"https://s.sde.globo.com/media/person_role/2023/02/28/photo_220x220_qIjSxtN.png","pontos_num":0,"preco_num":3.75,"variacao_num":0,"media_num":0.7,"jogos_num":3},{"id":69029,"apelido":"Antônio Carlos Zago","posicao":"Técnico","posicao_abrev":"tec","foto":"https://s.sde.globo.com/media/person_role/2023/05/10/photo_220x220_QhbNvRM.png","pontos_num":4.03,"preco_num":5.99,"variacao_num":0.31,"media_num":3.89,"jogos_num":4},{"id":86841,"apelido":"Boschilia","posicao":"Meia","posicao_abrev":"mei","foto":"https://s.sde.globo.com/media/person_role/2022/08/12/8bbade4dbabca44eb3eda2767deda745_220x220.png","pontos_num":0,"preco_num":5.63,"variacao_num":-0.85,"media_num":4.75,"jogos_num":4},{"id":106202,"apelido":"Bruno Gomes","posicao":"Meia","posicao_abrev":"mei","foto":"https://s.sde.globo.com/media/person_role/2023/02/28/photo_220x220_wvinlkF.png","pontos_num":2.6,"preco_num":9.22,"variacao_num":-0.14,"media_num":4.4,"jogos_num":6},{"id":92291,"apelido":"Bruno Viana","posicao":"Zagueiro","posicao_abrev":"zag","foto":"https://s.sde.globo.com/media/person_role/2023/02/28/photo_220x220_kVhXG72.png","pontos_num":4.5,"preco_num":3.64,"variacao_num":0.55,"media_num":2.22,"jogos_num":5},{"id":93166,"apelido":"Chancellor","posicao":"Zagueiro","posicao_abrev":"zag","foto":"https://s.sde.globo.com/media/person_role/2023/02/28/photo_220x220_ntiY1fN.png","pontos_num":-0.3,"preco_num":2.8,"variacao_num":-0.24,"media_num":0.67,"jogos_num":3},{"id":113384,"apelido":"Diogo Batista","posicao":"Lateral","posicao_abrev":"lat","foto":"https://s.sde.globo.com/media/person_role/2023/02/28/photo_220x220_SfVPzCz.png","pontos_num":0,"preco_num":1,"variacao_num":0,"media_num":0,"jogos_num":0},{"id":70449,"apelido":"Gabriel","posicao":"Goleiro","posicao_abrev":"gol","foto":"https://s.sde.globo.com/media/person_role/2023/02/28/photo_220x220_ovYbvXA.png","pontos_num":1,"preco_num":3.58,"variacao_num":0.04,"media_num":1.33,"jogos_num":6},{"id":116282,"apelido":"Gabriel Silva","posicao":"Meia","posicao_abrev":"mei","foto":"https://s.sde.globo.com/media/person_role/2023/04/20/photo_220x220_fzfvURk.png","pontos_num":0,"preco_num":1,"variacao_num":0,"media_num":0,"jogos_num":0},{"id":111644,"apelido":"Gustavo Vilar","posicao":"Zagueiro","posicao_abrev":"zag","foto":"https://s.sde.globo.com/media/person_role/2023/04/20/photo_220x220_WU7m9CP.png","pontos_num":0,"preco_num":1.32,"variacao_num":0,"media_num":0,"jogos_num":1},{"id":50856,"apelido":"Henrique","posicao":"Zagueiro","posicao_abrev":"zag","foto":"https://s.sde.globo.com/media/person_role/2023/02/28/photo_220x220_nAVtfcZ.png","pontos_num":0.5,"preco_num":2.81,"variacao_num":0.02,"media_num":0.8,"jogos_num":3},{"id":116461,"apelido":"Jamerson","posicao":"Lateral","posicao_abrev":"lat","foto":"https://s.sde.globo.com/media/person_role/2023/04/10/photo_220x220_FvosjlG.png","pontos_num":2,"preco_num":5.99,"variacao_num":-0.4,"media_num":2.98,"jogos_num":5},{"id":121796,"apelido":"Jean Pedroso","posicao":"Zagueiro","posicao_abrev":"zag","foto":"https://s.sde.globo.com/media/person_role/2023/02/28/photo_220x220_BsJge2e.png","pontos_num":0,"preco_num":1,"variacao_num":0,"media_num":0,"jogos_num":0},{"id":124358,"apelido":"João Vitor","posicao":"Lateral","posicao_abrev":"lat","foto":"https://s.sde.globo.com/media/person_role/2023/04/08/photo_220x220_99Ek8Df.png","pontos_num":0,"preco_num":1,"variacao_num":0,"media_num":0,"jogos_num":0},{"id":71829,"apelido":"Júnior Urso","posicao":"Meia","posicao_abrev":"mei","foto":"https://s.sde.globo.com/media/person_role/2023/02/28/photo_220x220_7ft8zu4.png","pontos_num":0,"preco_num":4.96,"variacao_num":0,"media_num":2.15,"jogos_num":2},{"id":118844,"apelido":"Kaio César","posicao":"Atacante","posicao_abrev":"ata","foto":"https://s.sde.globo.com/media/person_role/2023/02/28/photo_220x220_jGkK86O.png","pontos_num":0.5,"preco_num":3.92,"variacao_num":-0.16,"media_num":2.18,"jogos_num":6},{"id":98619,"apelido":"Kuscevic","posicao":"Zagueiro","posicao_abrev":"zag","foto":"https://s.sde.globo.com/media/person_role/2023/02/28/photo_220x220_qacVCwx.png","pontos_num":0,"preco_num":3.7,"variacao_num":0,"media_num":1.37,"jogos_num":3},{"id":100761,"apelido":"Liziero","posicao":"Meia","posicao_abrev":"mei","foto":"https://s.sde.globo.com/media/person_role/2023/02/28/photo_220x220_NUUHkjY.png","pontos_num":3.8,"preco_num":4.16,"variacao_num":0.68,"media_num":1.9,"jogos_num":4},{"id":88916,"apelido":"Luan Polli","posicao":"Goleiro","posicao_abrev":"gol","foto":"https://s.sde.globo.com/media/person_role/2023/02/28/photo_220x220_gZl1v6O.png","pontos_num":0,"preco_num":4,"variacao_num":0,"media_num":0,"jogos_num":0},{"id":110775,"apelido":"Marcão","posicao":"Goleiro","posicao_abrev":"gol","foto":"https://s.sde.globo.com/media/person_role/2023/02/28/photo_220x220_ur2aV6A.png","pontos_num":0,"preco_num":2,"variacao_num":0,"media_num":0,"jogos_num":0},{"id":88857,"apelido":"Marcelino Moreno","posicao":"Meia","posicao_abrev":"mei","foto":"https://s.sde.globo.com/media/person_role/2023/02/28/photo_220x220_S4cMFFx.png","pontos_num":8.2,"preco_num":4.54,"variacao_num":1.55,"media_num":3.4,"jogos_num":3},{"id":97969,"apelido":"Marcos Vinícius","posicao":"Lateral","posicao_abrev":"lat","foto":"https://s.sde.globo.com/media/person_role/2023/04/20/photo_220x220_ZD0eKFv.png","pontos_num":1.6,"preco_num":1.59,"variacao_num":0.17,"media_num":0.85,"jogos_num":2},{"id":104640,"apelido":"Matheus Bianqui","posicao":"Meia","posicao_abrev":"mei","foto":"https://s.sde.globo.com/media/person_role/2023/04/21/photo_220x220.png","pontos_num":0,"preco_num":2.55,"variacao_num":-0.3,"media_num":0.43,"jogos_num":3},{"id":111688,"apelido":"Matheus Cadorini","posicao":"Atacante","posicao_abrev":"ata","foto":"https://s.sde.globo.com/media/person_role/2023/02/28/photo_220x220_qDCu3iB.png","pontos_num":0,"preco_num":3,"variacao_num":0,"media_num":0,"jogos_num":0},{"id":107554,"apelido":"Natanael","posicao":"Lateral","posicao_abrev":"lat","foto":"https://s.sde.globo.com/media/person_role/2023/02/28/photo_220x220_0XMnyZN.png","pontos_num":0,"preco_num":10.48,"variacao_num":0,"media_num":6.7,"jogos_num":5},{"id":110623,"apelido":"Robinho","posicao":"Atacante","posicao_abrev":"ata","foto":"https://s.sde.globo.com/media/person_role/2023/02/28/photo_220x220_KfLKMAj.png","pontos_num":0,"preco_num":1,"variacao_num":0,"media_num":0,"jogos_num":0},{"id":84817,"apelido":"Robson","posicao":"Atacante","posicao_abrev":"ata","foto":"https://s.sde.globo.com/media/person_role/2023/02/28/photo_220x220_wdF92Dr.png","pontos_num":12.4,"preco_num":6.32,"variacao_num":1.77,"media_num":4.26,"jogos_num":5},{"id":86799,"apelido":"Rodrigo Pinho","posicao":"Atacante","posicao_abrev":"ata","foto":"https://s.sde.globo.com/media/person_role/2023/02/28/photo_220x220_28kb8HP.png","pontos_num":1.7,"preco_num":3.58,"variacao_num":-0.16,"media_num":1.88,"jogos_num":5},{"id":121797,"apelido":"Sidnei","posicao":"Goleiro","posicao_abrev":"gol","foto":"https://s.sde.globo.com/media/person_role/2023/02/28/photo_220x220_A2xBlsx.png","pontos_num":0,"preco_num":1,"variacao_num":0,"media_num":0,"jogos_num":0},{"id":112367,"apelido":"Thalisson Gabriel","posicao":"Zagueiro","posicao_abrev":"zag","foto":"https://s.sde.globo.com/media/person_role/2023/02/28/photo_220x220_fY8etYF.png","pontos_num":0,"preco_num":1,"variacao_num":0,"media_num":0,"jogos_num":0},{"id":122293,"apelido":"Thiago Dombroski","posicao":"Zagueiro","posicao_abrev":"zag","foto":"https://s.sde.globo.com/media/person_role/2023/05/11/photo_220x220_XH1tvmy.png","pontos_num":0,"preco_num":0.69,"variacao_num":0,"media_num":-0.3,"jogos_num":1},{"id":105433,"apelido":"Trindade","posicao":"Meia","posicao_abrev":"mei","foto":"https://s.sde.globo.com/media/person_role/2023/02/28/photo_220x220_IfD8fQ4.png","pontos_num":0,"preco_num":4,"variacao_num":0,"media_num":0,"jogos_num":0},{"id":86410,"apelido":"Victor Luis","posicao":"Lateral","posicao_abrev":"lat","foto":"https://s.sde.globo.com/media/person_role/2023/02/28/photo_220x220_cjqZYOH.png","pontos_num":0.5,"preco_num":2.47,"variacao_num":-0.14,"media_num":0.48,"jogos_num":5},{"id":107803,"apelido":"Wesley","posicao":"Atacante","posicao_abrev":"ata","foto":"https://s.sde.globo.com/media/person_role/2023/04/20/photo_220x220_KnKkZDT.png","pontos_num":0,"preco_num":3,"variacao_num":0,"media_num":0,"jogos_num":0},{"id":77809,"apelido":"William Pottker","posicao":"Atacante","posicao_abrev":"ata","foto":"https://s.sde.globo.com/media/person_role/2023/02/28/photo_220x220_yjb57GF.png","pontos_num":0,"preco_num":3.27,"variacao_num":0,"media_num":1.07,"jogos_num":3},{"id":63058,"apelido":"Willian Farias","posicao":"Meia","posicao_abrev":"mei","foto":"https://s.sde.globo.com/media/person_role/2023/02/28/photo_220x220_FaZq8Ny.png","pontos_num":0,"preco_num":3.8,"variacao_num":0,"media_num":2.43,"jogos_num":3},{"id":80076,"apelido":"Zé Roberto","posicao":"Atacante","posicao_abrev":"ata","foto":"https://s.sde.globo.com/media/person_role/2023/04/10/photo_220x220_Mzobxer.png","pontos_num":5.3,"preco_num":4.31,"variacao_num":0.26,"media_num":3.73,"jogos_num":4}]}},"context":{}}