{
  "id": 1371,
  "nome_fantasia": "Cuiabá",
  "clube_abrev": "CUI",
  "escudo_60": "https://s.glbimg.com/es/sde/f/organizacoes/2014/04/16/cuiaba65.png",
  "posicao": 17,
  "atletas": [
    {
      "id": 88033,
      "apelido": "Alan Empereur",
      "posicao": "Zagueiro",
      "posicao_abrev": "zag",
      "foto": "https://s.glbimg.com/es/sde/f/2022/07/20/5db43ec8756f6951151160f78ec748cb_140x140.png",
      "pontos_num": 0.4,
      "preco_num": 4.62,
      "variacao_num": -0.26,
      "media_num": 1.33,
      "jogos_num": 20
    },
    {
      "id": 97321,
      "apelido": "Alesson",
      "posicao": "Atacante",
      "posicao_abrev": "ata",
      "foto": "https://s.glbimg.com/es/sde/f/2022/02/23/712ddec1e1d5a64377efd6d330d2a984_140x140.png",
      "pontos_num": 0,
      "preco_num": 5.27,
      "variacao_num": 0,
      "media_num": 2.51,
      "jogos_num": 19
    },
    {
      "id": 106159,
      "apelido": "Alexandre Melo",
      "posicao": "Lateral",
      "posicao_abrev": "lat",
      "foto": "https://s.glbimg.com/es/sde/f/2021/05/28/47904876bb82a940b74259ffd4608337_140x140.png",
      "pontos_num": 0,
      "preco_num": 2,
      "variacao_num": 0,
      "media_num": 0,
      "jogos_num": 0
    },
    {
      "id": 92146,
      "apelido": "André Luís",
      "posicao": "Atacante",
      "posicao_abrev": "ata",
      "foto": "https://s.glbimg.com/es/sde/f/2022/02/23/4ba86feb09facb90b3a01b1712c3c8f5_140x140.png",
      "pontos_num": 2.3,
      "preco_num": 4.43,
      "variacao_num": 0.03,
      "media_num": 2.5,
      "jogos_num": 24
    },
    {
      "id": 111578,
      "apelido": "António Oliveira",
      "posicao": "Técnico",
      "posicao_abrev": "tec",
      "foto": "https://s.glbimg.com/es/sde/f/2021/04/27/21a131dcff78d521da3297e98526ce48_140x140.png",
      "pontos_num": 3.65,
      "preco_num": 7.59,
      "variacao_num": 0.35,
      "media_num": 3.48,
      "jogos_num": 20
    },
    {
      "id": 114892,
      "apelido": "Caio Hila",
      "posicao": "Lateral",
      "posicao_abrev": "lat",
      "foto": "https://s.glbimg.com/es/sde/f/2022/02/23/23b11c9392056eda52cf2816d37b89a0_140x140.png",
      "pontos_num": 0,
      "preco_num": 1,
      "variacao_num": 0,
      "media_num": 0,
      "jogos_num": 0
    },
    {
      "id": 104519,
      "apelido": "Camilo",
      "posicao": "Meia",
      "posicao_abrev": "mei",
      "foto": "https://s.glbimg.com/es/sde/f/2022/02/23/960b7b2641de9da54e54550f285f7f85_140x140.png",
      "pontos_num": 3.4,
      "preco_num": 3.91,
      "variacao_num": 0.15,
      "media_num": 1.71,
      "jogos_num": 19
    },
    {
      "id": 106540,
      "apelido": "Capellari",
      "posicao": "Goleiro",
      "posicao_abrev": "gol",
      "foto": "https://s.glbimg.com/es/sde/f/2022/02/23/87d740c03c7d93328314e0805a79be9f_140x140.png",
      "pontos_num": 0,
      "preco_num": 1,
      "variacao_num": 0,
      "media_num": 0,
      "jogos_num": 0
    },
    {
      "id": 88225,
      "apelido": "Daniel Guedes",
      "posicao": "Lateral",
      "posicao_abrev": "lat",
      "foto": "https://s.sde.globo.com/media/person_role/2022/04/21/eb1d1f53750f2ecb8c48b5caa3985a22_140x140.png",
      "pontos_num": 2.8,
      "preco_num": 3.38,
      "variacao_num": 0.63,
      "media_num": 2.78,
      "jogos_num": 12
    },
    {
      "id": 115986,
      "apelido": "Denilson",
      "posicao": "Meia",
      "posicao_abrev": "mei",
      "foto": "https://via.placeholder.com/140",
      "pontos_num": 2.4,
      "preco_num": 2.09,
      "variacao_num": 0.39,
      "media_num": 2.3,
      "jogos_num": 5
    },
    {
      "id": 92708,
      "apelido": "Deyverson",
      "posicao": "Atacante",
      "posicao_abrev": "ata",
      "foto": "https://s.glbimg.com/es/sde/f/2022/08/04/0f29963b959d422652eae53503f20f1f_140x140.png",
      "pontos_num": 12.7,
      "preco_num": 7.06,
      "variacao_num": 2.2,
      "media_num": 4.28,
      "jogos_num": 9
    },
    {
      "id": 101054,
      "apelido": "Felipe Marques",
      "posicao": "Atacante",
      "posicao_abrev": "ata",
      "foto": "https://s.glbimg.com/es/sde/f/2022/02/23/a6d728d21e5ecaec684045ba4d68975c_140x140.png",
      "pontos_num": 0,
      "preco_num": 2.69,
      "variacao_num": 0,
      "media_num": 0.81,
      "jogos_num": 17
    },
    {
      "id": 110607,
      "apelido": "Gabriel Pirani",
      "posicao": "Meia",
      "posicao_abrev": "mei",
      "foto": "https://s.glbimg.com/es/sde/f/2022/06/14/d526d926c095a507d46bffb0eb46a9a2_140x140.png",
      "pontos_num": 0.5,
      "preco_num": 2.38,
      "variacao_num": -0.05,
      "media_num": 1.69,
      "jogos_num": 11
    },
    {
      "id": 112327,
      "apelido": "Gustavo Nescau",
      "posicao": "Atacante",
      "posicao_abrev": "ata",
      "foto": "https://s.glbimg.com/es/sde/f/2021/09/20/768f5f056c491ffcf62c7383073dfab2_140x140.png",
      "pontos_num": -0.4,
      "preco_num": 2.2,
      "variacao_num": -0.8,
      "media_num": -0.4,
      "jogos_num": 1
    },
    {
      "id": 91639,
      "apelido": "Igor Cariús",
      "posicao": "Lateral",
      "posicao_abrev": "lat",
      "foto": "https://s.glbimg.com/es/sde/f/2022/02/23/fa3ebd08b3835164b2532b908f71ccfe_140x140.png",
      "pontos_num": 0.3,
      "preco_num": 4.34,
      "variacao_num": -0.6,
      "media_num": 2.03,
      "jogos_num": 11
    },
    {
      "id": 69010,
      "apelido": "João Carlos",
      "posicao": "Goleiro",
      "posicao_abrev": "gol",
      "foto": "https://s.glbimg.com/es/sde/f/2021/05/28/9d5caf065f11413aa6bf28e1d6b8acf8_140x140.png",
      "pontos_num": 2,
      "preco_num": 3.34,
      "variacao_num": 0.04,
      "media_num": 2.71,
      "jogos_num": 7
    },
    {
      "id": 104257,
      "apelido": "João Lucas",
      "posicao": "Lateral",
      "posicao_abrev": "lat",
      "foto": "https://s.glbimg.com/es/sde/f/2022/02/23/9aab91f181711232b92dd27558ae246d_140x140.png",
      "pontos_num": -0.1,
      "preco_num": 6.37,
      "variacao_num": -0.5,
      "media_num": 2.97,
      "jogos_num": 26
    },
    {
      "id": 109563,
      "apelido": "Joaquim",
      "posicao": "Zagueiro",
      "posicao_abrev": "zag",
      "foto": "https://s.glbimg.com/es/sde/f/2021/06/04/9af680e828bdcbc3a28ff0dbfc34f2e5_140x140.png",
      "pontos_num": 2.4,
      "preco_num": 4.95,
      "variacao_num": 0.32,
      "media_num": 4.38,
      "jogos_num": 18
    },
    {
      "id": 78580,
      "apelido": "Jonathan Cafu",
      "posicao": "Atacante",
      "posicao_abrev": "ata",
      "foto": "https://s.glbimg.com/es/sde/f/2021/05/28/3c667df8f70bf19082f021fa20403c6c_140x140.png",
      "pontos_num": 0,
      "preco_num": 2.26,
      "variacao_num": 0,
      "media_num": 0.44,
      "jogos_num": 8
    },
    {
      "id": 115830,
      "apelido": "Juan Ojeda",
      "posicao": "Zagueiro",
      "posicao_abrev": "zag",
      "foto": "https://s.glbimg.com/es/sde/f/2022/02/23/329e0ce48997a983d07303483e540281_140x140.png",
      "pontos_num": 0,
      "preco_num": 3,
      "variacao_num": 0,
      "media_num": 0,
      "jogos_num": 0
    },
    {
      "id": 108148,
      "apelido": "Lucas Cardoso ",
      "posicao": "Meia",
      "posicao_abrev": "mei",
      "foto": "https://s.glbimg.com/es/sde/f/2021/09/04/feab153e5104280ed7ed8cf60b5db070_140x140.png",
      "pontos_num": 0,
      "preco_num": 2,
      "variacao_num": 0,
      "media_num": 0,
      "jogos_num": 0
    },
    {
      "id": 78856,
      "apelido": "Marcão Silva",
      "posicao": "Meia",
      "posicao_abrev": "mei",
      "foto": "https://s.glbimg.com/es/sde/f/2022/02/23/1137efd5de0473f1c88c49348353a899_140x140.png",
      "pontos_num": 0.9,
      "preco_num": 2.41,
      "variacao_num": 0.17,
      "media_num": 0.96,
      "jogos_num": 19
    },
    {
      "id": 70666,
      "apelido": "Marllon",
      "posicao": "Zagueiro",
      "posicao_abrev": "zag",
      "foto": "https://s.glbimg.com/es/sde/f/2022/02/23/8d45db89a011dd77410922983889ff15_140x140.png",
      "pontos_num": 0,
      "preco_num": 7.36,
      "variacao_num": 0,
      "media_num": 3.21,
      "jogos_num": 27
    },
    {
      "id": 113010,
      "apelido": "Osorio",
      "posicao": "Meia",
      "posicao_abrev": "mei",
      "foto": "https://s.glbimg.com/es/sde/f/2022/02/23/e978cacf512124a39a2efe2b6b5d8164_140x140.png",
      "pontos_num": 1.4,
      "preco_num": 2.05,
      "variacao_num": -0.12,
      "media_num": 1.18,
      "jogos_num": 15
    },
    {
      "id": 63172,
      "apelido": "Paulão",
      "posicao": "Zagueiro",
      "posicao_abrev": "zag",
      "foto": "https://s.glbimg.com/es/sde/f/2022/02/23/962044a3dba4ade297a566c4d7f73d40_140x140.png",
      "pontos_num": 0,
      "preco_num": 3.49,
      "variacao_num": 0,
      "media_num": 1.58,
      "jogos_num": 10
    },
    {
      "id": 101573,
      "apelido": "Pepê",
      "posicao": "Meia",
      "posicao_abrev": "mei",
      "foto": "https://s.glbimg.com/es/sde/f/2022/02/23/f7d3a51faa57213871975b0e01258892_140x140.png",
      "pontos_num": 5.5,
      "preco_num": 6.78,
      "variacao_num": 0.95,
      "media_num": 3.21,
      "jogos_num": 23
    },
    {
      "id": 78867,
      "apelido": "Rafael Gava",
      "posicao": "Meia",
      "posicao_abrev": "mei",
      "foto": "https://s.glbimg.com/es/sde/f/2022/02/23/16687c4ddc3ae72291f2729ad61ed092_140x140.png",
      "pontos_num": 0,
      "preco_num": 3.07,
      "variacao_num": 0,
      "media_num": 1.32,
      "jogos_num": 20
    },
    {
      "id": 107039,
      "apelido": "Ricardo Cerqueira",
      "posicao": "Zagueiro",
      "posicao_abrev": "zag",
      "foto": "https://s.sde.globo.com/media/person_role/2022/09/28/photo_140x140.png",
      "pontos_num": 0,
      "preco_num": 1,
      "variacao_num": 0,
      "media_num": 0,
      "jogos_num": 0
    },
    {
      "id": 105547,
      "apelido": "Rikelme",
      "posicao": "Meia",
      "posicao_abrev": "mei",
      "foto": "https://s.glbimg.com/es/sde/f/2021/05/28/a067031810b555578d08ab063cd3701e_140x140.png",
      "pontos_num": 0,
      "preco_num": 1,
      "variacao_num": 0,
      "media_num": 0,
      "jogos_num": 0
    },
    {
      "id": 108659,
      "apelido": "Rivas",
      "posicao": "Meia",
      "posicao_abrev": "mei",
      "foto": "https://s.glbimg.com/es/sde/f/2022/02/23/1f9a18c6a38ce7b0c86a89f400ac4bb8_140x140.png",
      "pontos_num": 0,
      "preco_num": 2.11,
      "variacao_num": 0,
      "media_num": 0.86,
      "jogos_num": 5
    },
    {
      "id": 61033,
      "apelido": "Rodriguinho",
      "posicao": "Meia",
      "posicao_abrev": "mei",
      "foto": "https://s.glbimg.com/es/sde/f/2022/02/23/da202da4fb23bc636936f60651108982_140x140.png",
      "pontos_num": 0,
      "preco_num": 6.72,
      "variacao_num": 0,
      "media_num": 2.75,
      "jogos_num": 26
    },
    {
      "id": 86764,
      "apelido": "Sidcley",
      "posicao": "Lateral",
      "posicao_abrev": "lat",
      "foto": "https://s.glbimg.com/es/sde/f/2022/08/04/f1b96cd2e1a5c62c2aec694945991675_140x140.png",
      "pontos_num": 0,
      "preco_num": 4.7,
      "variacao_num": 0,
      "media_num": 3.02,
      "jogos_num": 6
    },
    {
      "id": 60852,
      "apelido": "Uendel",
      "posicao": "Lateral",
      "posicao_abrev": "lat",
      "foto": "https://s.glbimg.com/es/sde/f/2022/02/23/80aa17d4669a6357c0620eb0988e839e_140x140.png",
      "pontos_num": 0,
      "preco_num": 4.29,
      "variacao_num": 0,
      "media_num": 1.76,
      "jogos_num": 15
    },
    {
      "id": 85423,
      "apelido": "Valdívia",
      "posicao": "Meia",
      "posicao_abrev": "mei",
      "foto": "https://s.glbimg.com/es/sde/f/2022/02/23/ec8d7f67b026fc679f8ac3b10514eefd_140x140.png",
      "pontos_num": 3.7,
      "preco_num": 6.04,
      "variacao_num": 0.32,
      "media_num": 2.42,
      "jogos_num": 25
    },
    {
      "id": 98496,
      "apelido": "Vinícius",
      "posicao": "Goleiro",
      "posicao_abrev": "gol",
      "foto": "https://s.glbimg.com/es/sde/f/2022/02/23/7e55afddc960930adc82975477d86b1a_140x140.png",
      "pontos_num": 0,
      "preco_num": 1,
      "variacao_num": 0,
      "media_num": 0,
      "jogos_num": 0
    },
    {
      "id": 120684,
      "apelido": "Vinícius Boff",
      "posicao": "Atacante",
      "posicao_abrev": "ata",
      "foto": "https://s.sde.globo.com/media/person_role/2022/09/18/photo_140x140_gyZwVPH.png",
      "pontos_num": 0,
      "preco_num": 1,
      "variacao_num": 0,
      "media_num": 0,
      "jogos_num": 0
    },
    {
      "id": 51413,
      "apelido": "Walter",
      "posicao": "Goleiro",
      "posicao_abrev": "gol",
      "foto": "https://s.glbimg.com/es/sde/f/2021/05/28/50f29a94dff6b578111f33d689953f3c_140x140.png",
      "pontos_num": 0,
      "preco_num": 11.76,
      "variacao_num": 0,
      "media_num": 3.92,
      "jogos_num": 23
    }
  ]
}