{
  "ano": 2020,
  "atleta_id": 100830,
  "apelido": "Brenno",
  "clube": "Grêmio",
  "clube_id": 284,
  "posicao": "Goleiro",
  "rodadas": [
    1,
    2,
    3
  ],
  "pontos": [
    0,
    0,
    0
  ],
  "precos": [
    1,
    1,
    1
  ],
  "variacoes": [
    0,
    0,
    0
  ],
  "medias": [
    0,
    0,
    0
  ],
  "partidas": [
    {
      "rodada_id": 1,
      "clube_casa": "Grêmio",
      "clube_casa_id": 284,
      "clube_visitante": "Fluminense",
      "clube_casa_abrev": "GRE",
      "clube_casa_escudo": "https://s.glbimg.com/es/sde/f/organizacoes/2014/04/14/gremio_60x60.png",
      "clube_visitante_id": 266,
      "clube_visitante_abrev": "FLU",
      "clube_visitante_escudo": "https://s.glbimg.com/es/sde/f/organizacoes/2014/04/14/fluminense_60x60.png",
      "placar_oficial_mandante": 1,
      "placar_oficial_visitante": 0
    },
    {
      "rodada_id": 2,
      "clube_casa": "Ceará",
      "clube_casa_id": 354,
      "clube_visitante": "Grêmio",
      "clube_casa_abrev": "CEA",
      "clube_casa_escudo": "https://s.glbimg.com/es/sde/f/organizacoes/2019/10/10/ceara-65x65.png",
      "clube_visitante_id": 284,
      "clube_visitante_abrev": "GRE",
      "clube_visitante_escudo": "https://s.glbimg.com/es/sde/f/organizacoes/2014/04/14/gremio_60x60.png",
      "placar_oficial_mandante": 1,
      "placar_oficial_visitante": 1
    },
    {
      "rodada_id": 3,
      "clube_casa": "Grêmio",
      "clube_casa_id": 284,
      "clube_visitante": "Corinthians",
      "clube_casa_abrev": "GRE",
      "clube_casa_escudo": "https://s.glbimg.com/es/sde/f/organizacoes/2014/04/14/gremio_60x60.png",
      "clube_visitante_id": 264,
      "clube_visitante_abrev": "COR",
      "clube_visitante_escudo": "https://s.glbimg.com/es/sde/f/organizacoes/2019/09/30/Corinthians_65.png",
      "placar_oficial_mandante": 0,
      "placar_oficial_visitante": 0
    }
  ],
  "foto": "https://s.glbimg.com/es/sde/f/2020/07/19/1748daa635dc775b9136f10307a95ab1_140x140.png",
  "escudo_60": "https://s.glbimg.com/es/sde/f/organizacoes/2014/04/14/gremio_60x60.png",
  "scouts": {
    "rodada_id": 3,
    "rb": 0,
    "g": 0,
    "a": 0,
    "sg": 0,
    "fs": 0,
    "ff": 0,
    "fd": 0,
    "ft": 0,
    "dd": 0,
    "dp": 0,
    "gc": 0,
    "cv": 0,
    "ca": 0,
    "pp": 0,
    "gs": 0,
    "fc": 0,
    "i": 0,
    "pe": 0,
    "ds": 0,
    "pi": 0,
    "pontos_num": 0,
    "preco_num": 1,
    "variacao_num": 0,
    "media_num": 0,
    "jogos_num": 0,
    "posicao_abrev": "gol",
    "posicao": "Goleiro"
  }
}