{"hash":"c172775a48c5737d2e74498f4efd2bfaa398bdb5","data":{"pontuacao":{"ano":2022,"atleta_id":73318,"apelido":"Daniel Borges","clube":"Botafogo","clube_id":263,"posicao":"Lateral","foto":"https://s.glbimg.com/es/sde/f/2022/02/21/ce4af8aee58d0eef52f479ced5508ab5_140x140.png","escudo_60":"https://s.glbimg.com/es/sde/f/organizacoes/2019/02/04/botafogo-65.png","rodadas":[27,28,29,30,31,32,33,34,35,36,37],"pontos":[0,0,0,0,0,1.5,-0.6,3.1,1.5,6,10.8],"precos":[6.43,6.43,6.43,6.43,6.43,5.77,5.41,5.93,5.72,6.52,7.27],"variacoes":[0,0,0,0,0,-0.66,-0.36,0.52,-0.21,0.8,0.75],"medias":[2.75,2.75,2.75,2.75,2.75,2.69,2.53,2.56,2.51,2.66,2.99],"partidas":[{"clube_casa_abrev":"BOT","clube_casa_id":263,"clube_casa_escudo":"https://s.glbimg.com/es/sde/f/organizacoes/2019/02/04/botafogo-65.png","clube_visitante_abrev":"COR","clube_visitante_id":294,"clube_visitante_escudo":"https://s.glbimg.com/es/sde/f/organizacoes/2017/03/29/coritiba65.png","placar_oficial_mandante":2,"placar_oficial_visitante":0,"rodada_id":27},{"clube_casa_abrev":"GOI","clube_casa_id":290,"clube_casa_escudo":"https://s.glbimg.com/es/sde/f/organizacoes/2021/03/01/goias-65.png","clube_visitante_abrev":"BOT","clube_visitante_id":263,"clube_visitante_escudo":"https://s.glbimg.com/es/sde/f/organizacoes/2019/02/04/botafogo-65.png","placar_oficial_mandante":0,"placar_oficial_visitante":1,"rodada_id":28},{"clube_casa_abrev":"BOT","clube_casa_id":263,"clube_casa_escudo":"https://s.glbimg.com/es/sde/f/organizacoes/2019/02/04/botafogo-65.png","clube_visitante_abrev":"PAL","clube_visitante_id":275,"clube_visitante_escudo":"https://s.glbimg.com/es/sde/f/organizacoes/2014/04/14/palmeiras_60x60.png","placar_oficial_mandante":1,"placar_oficial_visitante":3,"rodada_id":29},{"clube_casa_abrev":"AVA","clube_casa_id":314,"clube_casa_escudo":"https://s.glbimg.com/es/sde/f/organizacoes/2018/09/04/escudo-avai-65x65.png","clube_visitante_abrev":"BOT","clube_visitante_id":263,"clube_visitante_escudo":"https://s.glbimg.com/es/sde/f/organizacoes/2019/02/04/botafogo-65.png","placar_oficial_mandante":1,"placar_oficial_visitante":2,"rodada_id":30},{"clube_casa_abrev":"SAO","clube_casa_id":276,"clube_casa_escudo":"https://s.glbimg.com/es/sde/f/organizacoes/2014/04/14/sao_paulo_60x60.png","clube_visitante_abrev":"BOT","clube_visitante_id":263,"clube_visitante_escudo":"https://s.glbimg.com/es/sde/f/organizacoes/2019/02/04/botafogo-65.png","placar_oficial_mandante":0,"placar_oficial_visitante":1,"rodada_id":31},{"clube_casa_abrev":"BOT","clube_casa_id":263,"clube_casa_escudo":"https://s.glbimg.com/es/sde/f/organizacoes/2019/02/04/botafogo-65.png","clube_visitante_abrev":"INT","clube_visitante_id":285,"clube_visitante_escudo":"https://s.glbimg.com/es/sde/f/organizacoes/2016/05/03/inter65.png","placar_oficial_mandante":0,"placar_oficial_visitante":1,"rodada_id":32},{"clube_casa_abrev":"FLU","clube_casa_id":266,"clube_casa_escudo":"https://s.glbimg.com/es/sde/f/organizacoes/2014/04/14/fluminense_60x60.png","clube_visitante_abrev":"BOT","clube_visitante_id":263,"clube_visitante_escudo":"https://s.glbimg.com/es/sde/f/organizacoes/2019/02/04/botafogo-65.png","placar_oficial_mandante":2,"placar_oficial_visitante":2,"rodada_id":33},{"clube_casa_abrev":"BOT","clube_casa_id":263,"clube_casa_escudo":"https://s.glbimg.com/es/sde/f/organizacoes/2019/02/04/botafogo-65.png","clube_visitante_abrev":"BRA","clube_visitante_id":280,"clube_visitante_escudo":"https://s.glbimg.com/es/sde/f/organizacoes/2020/01/01/65.png","placar_oficial_mandante":2,"placar_oficial_visitante":1,"rodada_id":34},{"clube_casa_abrev":"BOT","clube_casa_id":263,"clube_casa_escudo":"https://s.glbimg.com/es/sde/f/organizacoes/2019/02/04/botafogo-65.png","clube_visitante_abrev":"CUI","clube_visitante_id":1371,"clube_visitante_escudo":"https://s.glbimg.com/es/sde/f/organizacoes/2014/04/16/cuiaba65.png","placar_oficial_mandante":0,"placar_oficial_visitante":2,"rodada_id":35},{"clube_casa_abrev":"ATL","clube_casa_id":282,"clube_casa_escudo":"https://s.glbimg.com/es/sde/f/organizacoes/2017/11/23/Atletico-Mineiro-escudo65px.png","clube_visitante_abrev":"BOT","clube_visitante_id":263,"clube_visitante_escudo":"https://s.glbimg.com/es/sde/f/organizacoes/2019/02/04/botafogo-65.png","placar_oficial_mandante":0,"placar_oficial_visitante":2,"rodada_id":36},{"clube_casa_abrev":"BOT","clube_casa_id":263,"clube_casa_escudo":"https://s.glbimg.com/es/sde/f/organizacoes/2019/02/04/botafogo-65.png","clube_visitante_abrev":"SAN","clube_visitante_id":277,"clube_visitante_escudo":"https://s.glbimg.com/es/sde/f/organizacoes/2014/04/14/santos_60x60.png","placar_oficial_mandante":3,"placar_oficial_visitante":0,"rodada_id":37}],"scouts":{"ultima_rodada":37,"g":1,"a":3,"sg":7,"fs":13,"ff":5,"fd":2,"ft":0,"de":0,"dp":0,"gc":0,"cv":1,"ca":2,"pp":0,"gs":0,"fc":18,"i":1,"ds":33,"pi":252,"ps":0,"pc":0,"pontos_num":10.8,"preco_num":7.27,"variacao_num":0.75,"media_num":2.99,"jogos_num":25,"posicao_abrev":"lat","posicao":"Lateral"}}},"context":{}}